robust_http/__init__.py
robust_http/client.py
robust_http/tor_manager.py
robust_http/utils.py
robust_http-0.1.2.dist-info/LICENSE
robust_http-0.1.2.dist-info/METADATA
robust_http-0.1.2.dist-info/WHEEL
robust_http-0.1.2.dist-info/RECORD
