Metadata-Version: 2.1
Name: robust-http
Version: 0.1.2
Summary: High-level HTTP client with caching, UA rotation, retries, and optional Tor support.
Home-page: https://github.com/therealbct/robust_http
License: MIT
Keywords: http,requests,caching,tor,scraping,retry
Author: therealbct
Author-email: therealbct@users.noreply.github.com
Requires-Python: >=3.9,<4.0
Classifier: License :: OSI Approved :: MIT License
Classifier: Operating System :: OS Independent
Classifier: Programming Language :: Python :: 3
Classifier: Programming Language :: Python :: 3.9
Classifier: Programming Language :: Python :: 3.10
Classifier: Programming Language :: Python :: 3.11
Classifier: Programming Language :: Python :: 3.12
Provides-Extra: tor
Requires-Dist: fake_useragent (>=0.1,<4.0)
Requires-Dist: requests (>=2.25,<3.0)
Requires-Dist: requests_cache (>=0.9,<3.0)
Requires-Dist: stem (>=1.8,<3.0) ; extra == "tor"
Project-URL: Documentation, https://github.com/therealbct/robust_http#readme
Project-URL: Repository, https://github.com/therealbct/robust_http
